{
  "env": {
    "browser": true,
    "es2022": true,
    "node": true,
    "jest": true
  },
  "extends": ["eslint:recommended"],
  "parser": "@typescript-eslint/parser",
  "parserOptions": {
    "ecmaVersion": 2022,
    "sourceType": "module",
    "ecmaFeatures": {
      "jsx": true
    }
  },
  "plugins": ["@typescript-eslint"],
  "ignorePatterns": [
    "dist/",
    "build/",
    "node_modules/",
    "**/*.generated.*",
    "**/generated/",
    "**/*.d.ts",
    "**/*.js.map",
    "**/*.min.js",
    "**/coverage/",
    "**/.next/",
    "**/.turbo/",
    "**/.storybook-out/",
    "**/storybook-static/",
    "**/*.config.js",
    "**/*.config.ts",
    "**/jest.config.*",
    "**/eslint.config.*",
    "**/webpack.config.*",
    "**/vite.config.*",
    "**/next.config.*",
    "**/postcss.config.*",
    "**/tailwind.config.*",
    "**/turbo.json",
    "**/tsconfig.json",
    "**/package.json",
    "**/pnpm-lock.yaml",
    "**/yarn.lock",
    "**/package-lock.json",
    "**/*.md",
    "**/*.yml",
    "**/*.yaml",
    "**/Dockerfile*",
    "**/docker-compose*.yml",
    "**/docker-compose*.yaml",
    "**/*.sh",
    "**/*.bat",
    "**/*.ps1",
    "**/scripts/",
    "**/migrations/",
    "**/seeds/"
  ],
  "rules": {
    "@typescript-eslint/no-explicit-any": "off",
    "@typescript-eslint/no-unused-vars": "off",
    "@typescript-eslint/no-unsafe-function-type": "off",
    "@typescript-eslint/no-unsafe-assignment": "off",
    "@typescript-eslint/no-unsafe-member-access": "off",
    "@typescript-eslint/no-unsafe-call": "off",
    "@typescript-eslint/no-unsafe-return": "off",
    "@typescript-eslint/no-unsafe-argument": "off",
    "@typescript-eslint/no-misused-promises": "off",
    "@typescript-eslint/require-await": "off",
    "@typescript-eslint/no-floating-promises": "off",
    "@typescript-eslint/await-thenable": "off",
    "@typescript-eslint/no-unnecessary-type-assertion": "off",
    "@typescript-eslint/prefer-nullish-coalescing": "off",
    "@typescript-eslint/prefer-optional-chain": "off",
    "@typescript-eslint/no-non-null-assertion": "off",
    "@typescript-eslint/no-extra-non-null-assertion": "off",
    "@typescript-eslint/no-var-requires": "off",
    "no-undef": "off",
    "no-unused-vars": "off",
    "no-redeclare": "off",
    "no-console": "off",
    "no-debugger": "off",
    "semi": ["error", "always"],
    "quotes": ["error", "single"],
    "indent": "off",
    "comma-dangle": ["error", "always-multiline"],
    "object-curly-spacing": ["error", "always"],
    "array-bracket-spacing": ["error", "never"],
    "space-before-function-paren": ["error", "never"],
    "eol-last": ["error", "always"]
  }
}
